pony_sayz/__init__.py
pony_sayz/cli.py
pony_sayz/pony_sayz.py
pony_sayz-0.1.4.data/data/data/ace.pony
pony_sayz-0.1.4.data/data/data/rainbow.pony
pony_sayz-0.1.4.dist-info/AUTHORS.rst
pony_sayz-0.1.4.dist-info/LICENSE
pony_sayz-0.1.4.dist-info/METADATA
pony_sayz-0.1.4.dist-info/WHEEL
pony_sayz-0.1.4.dist-info/entry_points.txt
pony_sayz-0.1.4.dist-info/top_level.txt
pony_sayz-0.1.4.dist-info/RECORD
