Metadata-Version: 2.1
Name: pony-sayz
Version: 0.1.4
Summary: Pony says the message that you pass as parameter.
Home-page: https://github.com/paulospx/pony_sayz
Author: Paulo Paixao
Author-email: pssp25@hotmail.com
License: MIT license
Keywords: pony_sayz
Platform: UNKNOWN
Classifier: Development Status :: 2 - Pre-Alpha
Classifier: Intended Audience :: Developers
Classifier: License :: OSI Approved :: MIT License
Classifier: Natural Language :: English
Classifier: Programming Language :: Python :: 3
Classifier: Programming Language :: Python :: 3.5
Classifier: Programming Language :: Python :: 3.6
Classifier: Programming Language :: Python :: 3.7
Classifier: Programming Language :: Python :: 3.8
Requires-Python: >=3.5
